human_lambdas/__init__.py
human_lambdas/data_handler/csv_utils.py
human_lambdas/data_handler/data_schema.py
human_lambdas/data_handler/data_sync.py
human_lambdas/data_handler/data_transformation.py
human_lambdas/data_handler/data_validation.py
human_lambdas/data_handler/tests/__init__.py
human_lambdas/data_handler/tests/factories.py
human_lambdas/data_handler/tests/test_validators.py
human_lambdas/external/__init__.py
human_lambdas/external/authentication.py
human_lambdas/external/migrations/0001_initial.py
human_lambdas/external/migrations/__init__.py
human_lambdas/external/models.py
human_lambdas/external/serializers.py
human_lambdas/external/tests/__init__.py
human_lambdas/external/tests/test_flush.py
human_lambdas/external/tests/test_get_completed_list.py
human_lambdas/external/tests/test_integromat.py
human_lambdas/external/tests/test_task_creation.py
human_lambdas/external/tests/test_zapier_hooks.py
human_lambdas/external/urls.py
human_lambdas/external/views.py
human_lambdas/external/zapier.py
human_lambdas/frontend.tgz
human_lambdas/hl_cli.py
human_lambdas/hl_rest_api/__init__.py
human_lambdas/hl_rest_api/analytics.py
human_lambdas/hl_rest_api/email_client.py
human_lambdas/hl_rest_api/hl_client.py
human_lambdas/hl_rest_api/settings.py
human_lambdas/hl_rest_api/urls.py
human_lambdas/hl_rest_api/utils.py
human_lambdas/hl_rest_api/wsgi.py
human_lambdas/manage.py
human_lambdas/metrics/__init__.py
human_lambdas/metrics/tests/__init__.py
human_lambdas/metrics/tests/test_handling_time.py
human_lambdas/metrics/tests/test_metrics.py
human_lambdas/metrics/views.py
human_lambdas/middleware.py
human_lambdas/organization_handler/__init__.py
human_lambdas/organization_handler/serializers.py
human_lambdas/organization_handler/tests/__init__.py
human_lambdas/organization_handler/tests/test_organizations.py
human_lambdas/organization_handler/views.py
human_lambdas/templates_handler/tests/t.json
human_lambdas/templates_handler/tests/test_templates.py
human_lambdas-1.0.51.dist-info/entry_points.txt
human_lambdas-1.0.51.dist-info/WHEEL
human_lambdas-1.0.51.dist-info/METADATA
human_lambdas-1.0.51.dist-info/RECORD
