Metadata-Version: 2.1
Name: human-lambdas
Version: 1.0.51
Summary: Open Source Human in the Loop platform for anyone to run their own private Mechanical Turk.
Home-page: https://github.com/Human-Lambdas/human-lambdas
License: Apache-2.0
Author: Human Lambdas Ltd.
Author-email: bernat@humanlambdas.com
Requires-Python: >=3.8,<4.0
Classifier: License :: OSI Approved :: Apache Software License
Classifier: Programming Language :: Python :: 3
Classifier: Programming Language :: Python :: 3.8
Classifier: Programming Language :: Python :: 3.9
Requires-Dist: Django (==2.2.13)
Requires-Dist: PyJWT (==1.7.1)
Requires-Dist: analytics-python (==1.2.9)
Requires-Dist: cchardet (==0.3.5)
Requires-Dist: click (==7.1.2)
Requires-Dist: django-cors-headers (==3.6.0)
Requires-Dist: django-next-prev (>=1.1.0,<2.0.0)
Requires-Dist: django-rest-hooks-tmp (==1.6.1)
Requires-Dist: djangorestframework (==3.12.2)
Requires-Dist: djangorestframework-simplejwt (==4.3.0)
Requires-Dist: drf-chunked-upload (==0.4.2)
Requires-Dist: drf-yasg2 (>=1.19.4,<2.0.0)
Requires-Dist: email-validator (==1.1.1)
Requires-Dist: google-auth (==1.24.0)
Requires-Dist: google-cloud-storage (==1.36.0)
Requires-Dist: gunicorn (==20.0.04)
Requires-Dist: psycopg2-binary (>=2.8.6,<2.9.0)
Requires-Dist: python-dotenv (>=0.17.1,<0.18.0)
Requires-Dist: requests (>=2.25.1,<3.0.0)
Requires-Dist: schema (==0.7.2)
Requires-Dist: sendgrid (==6.4.8)
Requires-Dist: sentry-sdk (==0.19.5)
Requires-Dist: typing-extensions (==3.7.4)
Requires-Dist: whitenoise (>=5.2.0,<6.0.0)
